pydroplet/__init__.py
pydroplet/droplet.py
pydroplet/py.typed
pydroplet-2.3.4.dist-info/licenses/LICENSE
pydroplet-2.3.4.dist-info/METADATA
pydroplet-2.3.4.dist-info/WHEEL
pydroplet-2.3.4.dist-info/top_level.txt
pydroplet-2.3.4.dist-info/RECORD
