Metadata-Version: 2.4
Name: pydroplet
Version: 2.3.4
Summary: Package to connect to a Droplet device.
Author-email: Sarah Seidman <sarah.seidman@lixil.com>
License-Expression: MIT
Project-URL: Homepage, https://github.com/Hydrific/pydroplet
Project-URL: Issues, https://github.com/Hydrific/pydroplet/issues
Classifier: Programming Language :: Python :: 3
Classifier: Operating System :: OS Independent
Requires-Python: >=3.10
License-File: LICENSE
Requires-Dist: aiohttp
Dynamic: license-file
